{"_type":"export","__export_format":4,"__export_date":"2022-08-30T04:43:17.045Z","__export_source":"insomnia.desktop.app:v2022.5.1","resources":[{"_id":"req_4b4dae8e5a33476c8daf5846b03c8c65","parentId":"fld_32d4611223f04f29b65e731182ab4dbc","modified":1659478238300,"created":1659478220294,"url":"http://localhost:3001/api/categories/","name":"Get Categories","description":"","method":"GET","body":{},"parameters":[],"headers":[],"authentication":{},"metaSortKey":-1659478220294,"isPrivate":false,"settingStoreCookies":true,"settingSendCookies":true,"settingDisableRenderRequestBody":false,"settingEncodeUrl":true,"settingRebuildPath":true,"settingFollowRedirects":"global","_type":"request"},{"_id":"fld_32d4611223f04f29b65e731182ab4dbc","parentId":"fld_24eb0f31a7af46c79cf614ad516d5d0e","modified":1659478218641,"created":1659478218641,"name":"Category","description":"","environment":{},"environmentPropertyOrder":null,"metaSortKey":-1659478218641,"_type":"request_group"},{"_id":"fld_24eb0f31a7af46c79cf614ad516d5d0e","parentId":"wrk_ff3a16d2338545a6afb77e80eb489aba","modified":1659477601479,"created":1659477601479,"name":"Mie-E-Commerce","description":"","environment":{},"environmentPropertyOrder":null,"metaSortKey":-1659477601479,"_type":"request_group"},{"_id":"wrk_ff3a16d2338545a6afb77e80eb489aba","parentId":null,"modified":1658383379643,"created":1658383379643,"name":"New Document","description":"","scope":"design","_type":"workspace"},{"_id":"req_341d22cc31f842cb9ddd45cd408c165d","parentId":"fld_32d4611223f04f29b65e731182ab4dbc","modified":1661833495093,"created":1659478245603,"url":"http://localhost:3001/api/categories/6","name":"Get a Category","description":"","method":"GET","body":{},"parameters":[],"headers":[],"authentication":{},"metaSortKey":-1659477910861.5,"isPrivate":false,"settingStoreCookies":true,"settingSendCookies":true,"settingDisableRenderRequestBody":false,"settingEncodeUrl":true,"settingRebuildPath":true,"settingFollowRedirects":"global","_type":"request"},{"_id":"req_5e05ba68ca104f05ad260610c7ad2c5d","parentId":"fld_32d4611223f04f29b65e731182ab4dbc","modified":1661833912820,"created":1659478492556,"url":"http://localhost:3001/api/categories/","name":"Create a Category","description":"","method":"POST","body":{"mimeType":"application/json","text":"{\n\t\"categoryName\": \"Chicken feed\"\n}"},"parameters":[],"headers":[{"name":"Content-Type","value":"application/json","id":"pair_ba5814276ae449f19a6a67b79fcd5130"}],"authentication":{},"metaSortKey":-1659477872182.4375,"isPrivate":false,"settingStoreCookies":true,"settingSendCookies":true,"settingDisableRenderRequestBody":false,"settingEncodeUrl":true,"settingRebuildPath":true,"settingFollowRedirects":"global","_type":"request"},{"_id":"req_52342d21ec2d4396932ab5353fc28023","parentId":"fld_32d4611223f04f29b65e731182ab4dbc","modified":1661833920285,"created":1659478414071,"url":"http://localhost:3001/api/categories/6","name":"Update a Category","description":"","method":"PUT","body":{"mimeType":"application/json","text":"{\n\t\"categoryName\": \"Chicken unfeed\"\n}"},"parameters":[],"headers":[{"name":"Content-Type","value":"application/json","id":"pair_ba5814276ae449f19a6a67b79fcd5130"}],"authentication":{},"metaSortKey":-1659477833503.375,"isPrivate":false,"settingStoreCookies":true,"settingSendCookies":true,"settingDisableRenderRequestBody":false,"settingEncodeUrl":true,"settingRebuildPath":true,"settingFollowRedirects":"global","_type":"request"},{"_id":"req_087ba473158348e38a7d00c09c6e6833","parentId":"fld_32d4611223f04f29b65e731182ab4dbc","modified":1661833507572,"created":1659478379350,"url":"http://localhost:3001/api/categories/6","name":"Delete a Category","description":"","method":"DELETE","body":{},"parameters":[],"headers":[],"authentication":{},"metaSortKey":-1659477756145.25,"isPrivate":false,"settingStoreCookies":true,"settingSendCookies":true,"settingDisableRenderRequestBody":false,"settingEncodeUrl":true,"settingRebuildPath":true,"settingFollowRedirects":"global","_type":"request"},{"_id":"req_f346bf46d1d04a6186442d7b783a745b","parentId":"fld_cbd215df480d4b8e8f7c51346f61c1c4","modified":1661833522755,"created":1659478686328,"url":"http://localhost:3001/api/products","name":"Get Products","description":"","method":"GET","body":{},"parameters":[],"headers":[],"authentication":{},"metaSortKey":-1659478678837,"isPrivate":false,"settingStoreCookies":true,"settingSendCookies":true,"settingDisableRenderRequestBody":false,"settingEncodeUrl":true,"settingRebuildPath":true,"settingFollowRedirects":"global","_type":"request"},{"_id":"fld_cbd215df480d4b8e8f7c51346f61c1c4","parentId":"fld_24eb0f31a7af46c79cf614ad516d5d0e","modified":1659478757393,"created":1659478670549,"name":"Product","description":"","environment":{},"environmentPropertyOrder":null,"metaSortKey":-1659477910047.5,"_type":"request_group"},{"_id":"req_3a83f4d13dd941f4bd78f658fa99e8d3","parentId":"fld_cbd215df480d4b8e8f7c51346f61c1c4","modified":1661833948114,"created":1659478697361,"url":"http://localhost:3001/api/products/6","name":"Get a Product","description":"","method":"GET","body":{},"parameters":[],"headers":[],"authentication":{},"metaSortKey":-1659478449565.5,"isPrivate":false,"settingStoreCookies":true,"settingSendCookies":true,"settingDisableRenderRequestBody":false,"settingEncodeUrl":true,"settingRebuildPath":true,"settingFollowRedirects":"global","_type":"request"},{"_id":"req_791e21f1ea304d0086489c5f844a3e99","parentId":"fld_cbd215df480d4b8e8f7c51346f61c1c4","modified":1661834578885,"created":1661833303571,"url":"http://localhost:3001/api/products/","name":"Create Product","description":"","method":"POST","body":{"mimeType":"application/json","text":"{\n\t\"productName\": \"Basketball\",\n\t\"price\": 200.00,\n\t\"stock\": 3,\n\t\"tagIds\": [1, 2, 3, 4]\n}"},"parameters":[],"headers":[{"name":"Content-Type","value":"application/json","id":"pair_a4a2d09051584c4587176e43bbc16b71"}],"authentication":{},"metaSortKey":-1659478392247.625,"isPrivate":false,"settingStoreCookies":true,"settingSendCookies":true,"settingDisableRenderRequestBody":false,"settingEncodeUrl":true,"settingRebuildPath":true,"settingFollowRedirects":"global","_type":"request"},{"_id":"req_b9e92d731c544452888fdf2517a41ba3","parentId":"fld_cbd215df480d4b8e8f7c51346f61c1c4","modified":1661833961674,"created":1661833800124,"url":"http://localhost:3001/api/products/6","name":"Delete Product","description":"","method":"PUT","body":{"mimeType":"application/json","text":"{\n\t\"productName\": \"Basketball\",\n\t\"price\": 200.00,\n\t\"stock\": 0,\n\t\"tagIds\": [1]\n}"},"parameters":[],"headers":[{"name":"Content-Type","value":"application/json","id":"pair_a4a2d09051584c4587176e43bbc16b71"}],"authentication":{},"metaSortKey":-1659478377918.1562,"isPrivate":false,"settingStoreCookies":true,"settingSendCookies":true,"settingDisableRenderRequestBody":false,"settingEncodeUrl":true,"settingRebuildPath":true,"settingFollowRedirects":"global","_type":"request"},{"_id":"req_e227e9548dd74ff6a85645fbef5411e4","parentId":"fld_cbd215df480d4b8e8f7c51346f61c1c4","modified":1661833975142,"created":1659478733241,"url":"http://localhost:3001/api/products/6","name":"Delete a Product","description":"","method":"DELETE","body":{},"parameters":[],"headers":[],"authentication":{},"metaSortKey":-1659478334929.75,"isPrivate":false,"settingStoreCookies":true,"settingSendCookies":true,"settingDisableRenderRequestBody":false,"settingEncodeUrl":true,"settingRebuildPath":true,"settingFollowRedirects":"global","_type":"request"},{"_id":"req_e3ce749347fb4aeba25d58dd99494bc9","parentId":"fld_e0c76f23ca824138b10da3ed17ee9934","modified":1659477657294,"created":1658383379668,"url":"http://localhost:3001/api/tags/","name":"Get Tags","description":"","method":"GET","body":{},"parameters":[],"headers":[],"authentication":{},"metaSortKey":-1659477601429,"isPrivate":false,"settingStoreCookies":true,"settingSendCookies":true,"settingDisableRenderRequestBody":false,"settingEncodeUrl":true,"settingRebuildPath":true,"settingFollowRedirects":"global","_type":"request"},{"_id":"fld_e0c76f23ca824138b10da3ed17ee9934","parentId":"fld_24eb0f31a7af46c79cf614ad516d5d0e","modified":1659477624762,"created":1659477610237,"name":"Tags","description":"","environment":{},"environmentPropertyOrder":null,"metaSortKey":-1659477601454,"_type":"request_group"},{"_id":"req_1723c4cec45542e491f86dadbb71128e","parentId":"fld_e0c76f23ca824138b10da3ed17ee9934","modified":1661833993764,"created":1659477653107,"url":"http://localhost:3001/api/tags/9","name":"Get a Tag","description":"","method":"GET","body":{},"parameters":[],"headers":[],"authentication":{},"metaSortKey":-1659477601379,"isPrivate":false,"settingStoreCookies":true,"settingSendCookies":true,"settingDisableRenderRequestBody":false,"settingEncodeUrl":true,"settingRebuildPath":true,"settingFollowRedirects":"global","_type":"request"},{"_id":"req_5496cb908db14c2095c3499ce1d11b2f","parentId":"fld_e0c76f23ca824138b10da3ed17ee9934","modified":1661833987726,"created":1659477846452,"url":"http://localhost:3001/api/tags/","name":"Create a Tag","description":"","method":"POST","body":{"mimeType":"application/json","text":"{\n\t\"tag_name\": \"A new tag\"\n}"},"parameters":[],"headers":[{"name":"Content-Type","value":"application/json","id":"pair_e0791647ec664e99ab7f253734f29e07"}],"authentication":{},"metaSortKey":-1659477601329,"isPrivate":false,"settingStoreCookies":true,"settingSendCookies":true,"settingDisableRenderRequestBody":false,"settingEncodeUrl":true,"settingRebuildPath":true,"settingFollowRedirects":"global","_type":"request"},{"_id":"req_ffcf427b8d374996bd7f85a4e0bfe738","parentId":"fld_e0c76f23ca824138b10da3ed17ee9934","modified":1661834011606,"created":1659478168975,"url":"http://localhost:3001/api/tags/9","name":"Update a Tag","description":"","method":"PUT","body":{"mimeType":"application/json","text":"{\n\t\"tagName\": \"A new, updated tag\"\n}"},"parameters":[],"headers":[{"name":"Content-Type","value":"application/json","id":"pair_e0791647ec664e99ab7f253734f29e07"}],"authentication":{},"metaSortKey":-1659477601279,"isPrivate":false,"settingStoreCookies":true,"settingSendCookies":true,"settingDisableRenderRequestBody":false,"settingEncodeUrl":true,"settingRebuildPath":true,"settingFollowRedirects":"global","_type":"request"},{"_id":"req_276e11201ea249d4904c313163b3a113","parentId":"fld_e0c76f23ca824138b10da3ed17ee9934","modified":1661834020991,"created":1659478326504,"url":"http://localhost:3001/api/tags/9","name":"Delete a Tag","description":"","method":"DELETE","body":{},"parameters":[],"headers":[],"authentication":{},"metaSortKey":-1659477601229,"isPrivate":false,"settingStoreCookies":true,"settingSendCookies":true,"settingDisableRenderRequestBody":false,"settingEncodeUrl":true,"settingRebuildPath":true,"settingFollowRedirects":"global","_type":"request"},{"_id":"env_cd3f9a57cfbe8d3acc2c0b3b82b31adbb46649d3","parentId":"wrk_ff3a16d2338545a6afb77e80eb489aba","modified":1658383379661,"created":1658383379661,"name":"Base Environment","data":{},"dataPropertyOrder":null,"color":null,"isPrivate":false,"metaSortKey":1658383379661,"_type":"environment"},{"_id":"jar_cd3f9a57cfbe8d3acc2c0b3b82b31adbb46649d3","parentId":"wrk_ff3a16d2338545a6afb77e80eb489aba","modified":1661056465662,"created":1658383379665,"name":"Default Jar","cookies":[{"key":"connect.sid","value":"s%3AItExy8NCmRj3cua3-lgRnn42ltAJO9n_.Es67iEs30pIBcURp%2BnnBgdyd3H%2BEF%2FJNR4ELLpBnDRY","expires":"2022-09-04T04:34:25.000Z","domain":"localhost","path":"/","httpOnly":true,"extensions":["SameSite=Strict"],"hostOnly":true,"creation":"2022-08-03T18:15:58.770Z","lastAccessed":"2022-08-21T04:34:25.661Z","id":"9538997734211745"}],"_type":"cookie_jar"},{"_id":"spc_0df38ed3dd2c42e5be3a0eefbdd24451","parentId":"wrk_ff3a16d2338545a6afb77e80eb489aba","modified":1659478801268,"created":1658383379656,"fileName":"Boot Camp","contents":"","contentType":"yaml","_type":"api_spec"},{"_id":"uts_c59324fcb5554c51b3f4ddf6cadbd57a","parentId":"wrk_ff3a16d2338545a6afb77e80eb489aba","modified":1658383379670,"created":1658383379670,"name":"Example Test Suite","_type":"unit_test_suite"}]}